<?xml version="1.0" encoding="utf-8"?>
<Defs>
  <!-- #region Top -->
  <!-- Receiver -->
  <CWF.PartDef>
    <defName>Receiver</defName>
    <label>receiver</label>
    <group>Top</group>
    <order>0</order>
  </CWF.PartDef>

  <!-- Sight -->
  <CWF.PartDef>
    <defName>Sight</defName>
    <label>sight</label>
    <group>Top</group>
    <order>10</order>
    <fallbackTexturePath>CustomizeWeapon/Modules/Sight/4xScope/4xScope_o</fallbackTexturePath>
  </CWF.PartDef>

  <!-- Barrel -->
  <CWF.PartDef>
    <defName>Barrel</defName>
    <label>barrel</label>
    <group>Top</group>
    <order>30</order>
    <fallbackTexturePath>CustomizeWeapon/Modules/Barrel/ShortenedBarrel/ForChargeRifle_o</fallbackTexturePath>
  </CWF.PartDef>
  <!-- #endregion -->

  <!-- #region Left -->
  <!-- Stock -->
  <CWF.PartDef>
    <defName>Stock</defName>
    <label>stock</label>
    <group>Left</group>
    <order>0</order>
    <fallbackTexturePath>CustomizeWeapon/Modules/Stock/ExtendedStock/ForHellcatRifle_o</fallbackTexturePath>
  </CWF.PartDef>
  <!-- #endregion -->

  <!-- #region Right -->
  <!-- Muzzle -->
  <CWF.PartDef>
    <defName>Muzzle</defName>
    <label>muzzle</label>
    <group>Right</group>
    <order>0</order>
  </CWF.PartDef>

  <!-- Ammo -->
  <CWF.PartDef>
    <defName>Ammo</defName>
    <label>ammo</label>
    <group>Right</group>
    <order>10</order>
  </CWF.PartDef>
  <!-- #endregion -->

  <!-- #region Bottom -->
  <!-- Grip -->
  <CWF.PartDef>
    <defName>Grip</defName>
    <label>grip</label>
    <group>Bottom</group>
    <order>0</order>
    <fallbackTexturePath>CustomizeWeapon/Modules/Grip/CustomGrip/ForAssaultRifle_o</fallbackTexturePath>
  </CWF.PartDef>

  <!-- Trigger -->
  <CWF.PartDef>
    <defName>Trigger</defName>
    <label>trigger</label>
    <group>Bottom</group>
    <order>10</order>
  </CWF.PartDef>

  <!-- Magazine -->
  <CWF.PartDef>
    <defName>Magazine</defName>
    <label>magazine</label>
    <group>Bottom</group>
    <order>20</order>
    <fallbackTexturePath>CustomizeWeapon/Modules/Magazine/QuickMagazine/ForAssaultRifle_o</fallbackTexturePath>
  </CWF.PartDef>

  <!-- Underbarrel -->
  <CWF.PartDef>
    <defName>Underbarrel</defName>
    <label>underbarrel</label>
    <group>Bottom</group>
    <order>30</order>
    <fallbackTexturePath>CustomizeWeapon/Modules/Unberbarrel/AimAssistance/AimAssistance_o</fallbackTexturePath>
  </CWF.PartDef>
  <!-- #endregion -->
</Defs>